TeXCalc/__init__.py
TeXCalc/core.py
TeXCalc/defines.py
TeXCalc/exceptions.py
TeXCalc/fields.py
TeXCalc/processors.py
TeXCalc/tests.py
examples/__init__.py
examples/custom_hashmap.py
examples/usecases.py
texcalc-0.1.0.dist-info/LICENSE.txt
texcalc-0.1.0.dist-info/METADATA
texcalc-0.1.0.dist-info/WHEEL
texcalc-0.1.0.dist-info/top_level.txt
texcalc-0.1.0.dist-info/RECORD
